{
  "category": "learning",
  "name": "Learning Acceleration",
  "description": "Education, skill development, knowledge retention",
  "availableTags": [
    {
      "id": "7829564732190847046",
      "tag": "learning-education",
      "translations": [{
        "id": "7829564732190847146",
        "language": "en",
        "description": "Learning and educational systems"
      }]
    },
    {
      "id": "7829564732190847047",
      "tag": "adaptive-learning",
      "translations": [{
        "id": "7829564732190847147",
        "language": "en",
        "description": "Adaptive learning path creation"
      }]
    },
    {
      "id": "7829564732190847048",
      "tag": "skill-assessment",
      "translations": [{
        "id": "7829564732190847148",
        "language": "en",
        "description": "Skill evaluation and gap analysis"
      }]
    },
    {
      "id": "7829564732190847049",
      "tag": "language-learning",
      "translations": [{
        "id": "7829564732190847149",
        "language": "en",
        "description": "Language acquisition support"
      }]
    },
    {
      "id": "7829564732190847050",
      "tag": "knowledge-retention",
      "translations": [{
        "id": "7829564732190847150",
        "language": "en",
        "description": "Knowledge retention and recall"
      }]
    }
  ],
  "crossCuttingTags": [
    "planning",
    "generation",
    "coaching",
    "optimization",
    "analysis"
  ]
}