{
  "id": "7829564732190848759",
  "publicId": "candidate-assessor-v1",
  "resourceType": "Routine",
  "isPrivate": false,
  "permissions": "{}",
  "isInternal": false,
  "tags": [
    {
      "id": "7829564732190847081",
      "tag": "career",
      "translations": [
        {
          "id": "7829564732190847181",
          "language": "en",
          "description": "Career development"
        }
      ]
    },
    {
      "id": "7829564732190847090",
      "tag": "analysis",
      "translations": [
        {
          "id": "7829564732190847190",
          "language": "en",
          "description": "Analytical capabilities"
        }
      ]
    }
  ],
  "versions": [
    {
      "id": "7829564732190848760",
      "publicId": "candidate-assessor-v1-0",
      "versionLabel": "1.0.0",
      "versionNotes": "Initial version - Assesses candidate fit and preparation",
      "isComplete": true,
      "isPrivate": false,
      "versionIndex": 0,
      "isAutomatable": true,
      "resourceSubType": "RoutineGenerate",
      "config": {
        "__version": "1.0",
        "formInput": {
          "__version": "1.0",
          "schema": {
            "containers": [],
            "elements": [
              {
                "fieldName": "candidateProfile",
                "id": "candidate_profile_input",
                "label": "Candidate Profile",
                "type": "Text",
                "isRequired": true,
                "placeholder": "Resume, skills, and experience"
              },
              {
                "fieldName": "jobRequirements",
                "id": "job_requirements_input",
                "label": "Job Requirements",
                "type": "Text",
                "isRequired": true,
                "placeholder": "Job description and requirements"
              },
              {
                "fieldName": "companyFit",
                "id": "company_fit_input",
                "label": "Company Culture Info",
                "type": "JSON",
                "isRequired": false,
                "placeholder": "Company culture insights"
              }
            ]
          }
        },
        "formOutput": {
          "__version": "1.0",
          "schema": {
            "containers": [],
            "elements": [
              {
                "fieldName": "strengthsAnalysis",
                "id": "strengths_analysis_output",
                "label": "Candidate Strengths",
                "type": "JSON"
              },
              {
                "fieldName": "gapAnalysis",
                "id": "gap_analysis_output",
                "label": "Skill Gaps",
                "type": "JSON"
              },
              {
                "fieldName": "fitAssessment",
                "id": "fit_assessment_output",
                "label": "Company Fit Assessment",
                "type": "JSON"
              }
            ]
          }
        },
        "executionStrategy": "reasoning",
        "allowStrategyOverride": false
      },
      "translations": [
        {
          "id": "7829564732190848761",
          "language": "en",
          "name": "Candidate Assessor",
          "description": "Assesses candidate fit for position, analyzing strengths, gaps, and company alignment.",
          "instructions": "Provide candidate profile and job requirements. The routine will assess fit and identify gaps."
        }
      ]
    }
  ]
}