{
  "category": "content-creation",
  "name": "Digital Content Creation",
  "description": "Video content, tutorials, educational materials",
  "availableTags": [
    {
      "id": "7829564732190847081",
      "tag": "content-creation",
      "translations": [{
        "id": "7829564732190847181",
        "language": "en",
        "description": "Digital content creation"
      }]
    },
    {
      "id": "7829564732190847082",
      "tag": "video-production",
      "translations": [{
        "id": "7829564732190847182",
        "language": "en",
        "description": "Video content production"
      }]
    },
    {
      "id": "7829564732190847083",
      "tag": "tutorial-creation",
      "translations": [{
        "id": "7829564732190847183",
        "language": "en",
        "description": "Tutorial and guide creation"
      }]
    },
    {
      "id": "7829564732190847084",
      "tag": "educational-content",
      "translations": [{
        "id": "7829564732190847184",
        "language": "en",
        "description": "Educational material development"
      }]
    },
    {
      "id": "7829564732190847085",
      "tag": "assessment-design",
      "translations": [{
        "id": "7829564732190847185",
        "language": "en",
        "description": "Quiz and assessment creation"
      }]
    }
  ],
  "crossCuttingTags": [
    "generation",
    "planning",
    "automation",
    "coaching",
    "analysis"
  ]
}