{
  "id": "7829564732190847126",
  "publicId": "workout-build-v1",
  "resourceType": "Routine",
  "isPrivate": false,
  "permissions": "{}",
  "isInternal": false,
  "tags": [],
  "versions": [
    {
      "id": "7829564732190847127",
      "publicId": "workout-rtn-v1",
      "versionLabel": "1.0.0",
      "versionNotes": "Initial version",
      "isComplete": true,
      "isPrivate": false,
      "versionIndex": 0,
      "isAutomatable": true,
      "resourceSubType": "RoutineCode",
      "config": {
        "__version": "1.0",
        "callDataCode": {
          "__version": "1.0",
          "schema": {
            "language": "python",
            "code": "import json\nfrom datetime import datetime, timedelta\n\ndef create_workout_routine():\n    # Get inputs\n    fitness_goals = globals().get('fitness_goals', '')\n    equipment_available = globals().get('equipment_available', '')\n    schedule_availability = globals().get('schedule_availability', '')\n    experience_level = globals().get('experience_level', 'beginner')\n    time_per_session = globals().get('time_per_session', '30-45 minutes')\n    physical_limitations = globals().get('physical_limitations', '')\n    workout_preferences = globals().get('workout_preferences', '')\n    \n    # Define exercise database\n    exercises = {\n        'bodyweight': {\n            'upper_body': [\n                {'name': 'Push-ups', 'muscle_groups': ['chest', 'triceps', 'shoulders'], 'difficulty': 'beginner'},\n                {'name': 'Pull-ups/Chin-ups', 'muscle_groups': ['back', 'biceps'], 'difficulty': 'intermediate'},\n                {'name': 'Pike Push-ups', 'muscle_groups': ['shoulders', 'triceps'], 'difficulty': 'intermediate'},\n                {'name': 'Diamond Push-ups', 'muscle_groups': ['triceps', 'chest'], 'difficulty': 'intermediate'},\n                {'name': 'Tricep Dips', 'muscle_groups': ['triceps', 'shoulders'], 'difficulty': 'beginner'},\n                {'name': 'Wall Handstand', 'muscle_groups': ['shoulders', 'core'], 'difficulty': 'advanced'}\n            ],\n            'lower_body': [\n                {'name': 'Squats', 'muscle_groups': ['quads', 'glutes'], 'difficulty': 'beginner'},\n                {'name': 'Lunges', 'muscle_groups': ['quads', 'glutes', 'hamstrings'], 'difficulty': 'beginner'},\n                {'name': 'Jump Squats', 'muscle_groups': ['quads', 'glutes', 'calves'], 'difficulty': 'intermediate'},\n                {'name': 'Single-leg Glute Bridges', 'muscle_groups': ['glutes', 'hamstrings'], 'difficulty': 'intermediate'},\n                {'name': 'Calf Raises', 'muscle_groups': ['calves'], 'difficulty': 'beginner'},\n                {'name': 'Pistol Squats', 'muscle_groups': ['quads', 'glutes'], 'difficulty': 'advanced'}\n            ],\n            'core': [\n                {'name': 'Plank', 'muscle_groups': ['core', 'shoulders'], 'difficulty': 'beginner'},\n                {'name': 'Mountain Climbers', 'muscle_groups': ['core', 'shoulders'], 'difficulty': 'intermediate'},\n                {'name': 'Bicycle Crunches', 'muscle_groups': ['core'], 'difficulty': 'beginner'},\n                {'name': 'Russian Twists', 'muscle_groups': ['core', 'obliques'], 'difficulty': 'beginner'},\n                {'name': 'Dead Bug', 'muscle_groups': ['core'], 'difficulty': 'beginner'},\n                {'name': 'L-Sit', 'muscle_groups': ['core', 'hip_flexors'], 'difficulty': 'advanced'}\n            ],\n            'cardio': [\n                {'name': 'Burpees', 'muscle_groups': ['full_body'], 'difficulty': 'intermediate'},\n                {'name': 'High Knees', 'muscle_groups': ['legs', 'core'], 'difficulty': 'beginner'},\n                {'name': 'Jumping Jacks', 'muscle_groups': ['full_body'], 'difficulty': 'beginner'},\n                {'name': 'Butt Kicks', 'muscle_groups': ['hamstrings', 'calves'], 'difficulty': 'beginner'}\n            ]\n        },\n        'weights': {\n            'upper_body': [\n                {'name': 'Bench Press', 'muscle_groups': ['chest', 'triceps', 'shoulders'], 'difficulty': 'intermediate'},\n                {'name': 'Bent-over Rows', 'muscle_groups': ['back', 'biceps'], 'difficulty': 'intermediate'},\n                {'name': 'Overhead Press', 'muscle_groups': ['shoulders', 'triceps'], 'difficulty': 'intermediate'},\n                {'name': 'Bicep Curls', 'muscle_groups': ['biceps'], 'difficulty': 'beginner'},\n                {'name': 'Tricep Extensions', 'muscle_groups': ['triceps'], 'difficulty': 'beginner'},\n                {'name': 'Lateral Raises', 'muscle_groups': ['shoulders'], 'difficulty': 'beginner'}\n            ],\n            'lower_body': [\n                {'name': 'Deadlifts', 'muscle_groups': ['hamstrings', 'glutes', 'back'], 'difficulty': 'intermediate'},\n                {'name': 'Weighted Squats', 'muscle_groups': ['quads', 'glutes'], 'difficulty': 'intermediate'},\n                {'name': 'Romanian Deadlifts', 'muscle_groups': ['hamstrings', 'glutes'], 'difficulty': 'intermediate'},\n                {'name': 'Bulgarian Split Squats', 'muscle_groups': ['quads', 'glutes'], 'difficulty': 'intermediate'},\n                {'name': 'Hip Thrusts', 'muscle_groups': ['glutes'], 'difficulty': 'beginner'},\n                {'name': 'Calf Raises (weighted)', 'muscle_groups': ['calves'], 'difficulty': 'beginner'}\n            ]\n        },\n        'resistance_bands': {\n            'upper_body': [\n                {'name': 'Band Pull-aparts', 'muscle_groups': ['rear_delts', 'rhomboids'], 'difficulty': 'beginner'},\n                {'name': 'Band Rows', 'muscle_groups': ['back', 'biceps'], 'difficulty': 'beginner'},\n                {'name': 'Band Chest Press', 'muscle_groups': ['chest', 'triceps'], 'difficulty': 'beginner'},\n                {'name': 'Band Overhead Press', 'muscle_groups': ['shoulders'], 'difficulty': 'beginner'}\n            ],\n            'lower_body': [\n                {'name': 'Band Squats', 'muscle_groups': ['quads', 'glutes'], 'difficulty': 'beginner'},\n                {'name': 'Band Lateral Walks', 'muscle_groups': ['glutes', 'hip_abductors'], 'difficulty': 'beginner'},\n                {'name': 'Band Glute Bridges', 'muscle_groups': ['glutes'], 'difficulty': 'beginner'}\n            ]\n        }\n    }\n    \n    def determine_workout_split():\n        \"\"\"Determine workout split based on goals and availability\"\"\"\n        goals_lower = fitness_goals.lower()\n        \n        if '2' in schedule_availability or 'twice' in schedule_availability:\n            return 'full_body', 2\n        elif '3' in schedule_availability or 'three' in schedule_availability:\n            if 'strength' in goals_lower or 'muscle' in goals_lower:\n                return 'upper_lower', 3\n            else:\n                return 'full_body', 3\n        elif '4' in schedule_availability or 'four' in schedule_availability:\n            return 'upper_lower', 4\n        elif '5' in schedule_availability or 'five' in schedule_availability or '6' in schedule_availability:\n            return 'push_pull_legs', 6\n        else:\n            return 'full_body', 3  # Default\n    \n    def select_exercises_for_split(split_type, available_equipment):\n        \"\"\"Select appropriate exercises based on split and equipment\"\"\"\n        selected_exercises = {}\n        \n        # Determine available exercise categories\n        exercise_categories = ['bodyweight']\n        if 'weights' in available_equipment.lower() or 'dumbbell' in available_equipment.lower():\n            exercise_categories.append('weights')\n        if 'resistance' in available_equipment.lower() or 'band' in available_equipment.lower():\n            exercise_categories.append('resistance_bands')\n        \n        # Filter exercises by experience level\n        difficulty_levels = ['beginner']\n        if experience_level == 'intermediate':\n            difficulty_levels.append('intermediate')\n        elif experience_level == 'advanced':\n            difficulty_levels.extend(['intermediate', 'advanced'])\n        \n        if split_type == 'full_body':\n            selected_exercises['full_body'] = []\n            for category in exercise_categories:\n                if category in exercises:\n                    for muscle_group in exercises[category]:\n                        suitable_exercises = [\n                            ex for ex in exercises[category][muscle_group]\n                            if ex['difficulty'] in difficulty_levels\n                        ]\n                        selected_exercises['full_body'].extend(suitable_exercises[:2])  # Limit to 2 per group\n        \n        elif split_type == 'upper_lower':\n            selected_exercises['upper'] = []\n            selected_exercises['lower'] = []\n            \n            for category in exercise_categories:\n                if category in exercises:\n                    # Upper body\n                    for muscle_group in ['upper_body', 'core']:\n                        if muscle_group in exercises[category]:\n                            suitable_exercises = [\n                                ex for ex in exercises[category][muscle_group]\n                                if ex['difficulty'] in difficulty_levels\n                            ]\n                            selected_exercises['upper'].extend(suitable_exercises[:3])\n                    \n                    # Lower body\n                    if 'lower_body' in exercises[category]:\n                        suitable_exercises = [\n                            ex for ex in exercises[category]['lower_body']\n                            if ex['difficulty'] in difficulty_levels\n                        ]\n                        selected_exercises['lower'].extend(suitable_exercises[:4])\n        \n        elif split_type == 'push_pull_legs':\n            selected_exercises['push'] = []\n            selected_exercises['pull'] = []\n            selected_exercises['legs'] = []\n            \n            # This would be more complex - simplified for demo\n            for category in exercise_categories:\n                if category in exercises and 'upper_body' in exercises[category]:\n                    suitable_exercises = [\n                        ex for ex in exercises[category]['upper_body']\n                        if ex['difficulty'] in difficulty_levels\n                    ]\n                    # Simplified assignment\n                    selected_exercises['push'].extend(suitable_exercises[:3])\n                    selected_exercises['pull'].extend(suitable_exercises[:3])\n                \n                if category in exercises and 'lower_body' in exercises[category]:\n                    suitable_exercises = [\n                        ex for ex in exercises[category]['lower_body']\n                        if ex['difficulty'] in difficulty_levels\n                    ]\n                    selected_exercises['legs'].extend(suitable_exercises[:4])\n        \n        return selected_exercises\n    \n    def create_workout_schedule(split_type, days_per_week):\n        \"\"\"Create weekly workout schedule\"\"\"\n        schedule = {}\n        \n        if split_type == 'full_body':\n            workout_days = ['Monday', 'Wednesday', 'Friday'][:days_per_week]\n            for day in workout_days:\n                schedule[day] = 'Full Body Workout'\n        \n        elif split_type == 'upper_lower':\n            if days_per_week == 3:\n                schedule = {\n                    'Monday': 'Upper Body',\n                    'Wednesday': 'Lower Body',\n                    'Friday': 'Upper Body'\n                }\n            elif days_per_week == 4:\n                schedule = {\n                    'Monday': 'Upper Body',\n                    'Tuesday': 'Lower Body',\n                    'Thursday': 'Upper Body',\n                    'Friday': 'Lower Body'\n                }\n        \n        elif split_type == 'push_pull_legs':\n            schedule = {\n                'Monday': 'Push (Chest, Shoulders, Triceps)',\n                'Tuesday': 'Pull (Back, Biceps)',\n                'Wednesday': 'Legs (Quads, Hamstrings, Glutes)',\n                'Thursday': 'Push',\n                'Friday': 'Pull',\n                'Saturday': 'Legs'\n            }\n        \n        return schedule\n    \n    def generate_progression_plan():\n        \"\"\"Generate progression recommendations\"\"\"\n        progressions = {\n            'beginner': {\n                'week_1_2': 'Focus on form and consistency',\n                'week_3_4': 'Increase reps by 1-2 per exercise',\n                'week_5_6': 'Add 1 more set or increase difficulty',\n                'week_7_8': 'Introduce new exercises or increase intensity'\n            },\n            'intermediate': {\n                'week_1_2': 'Establish baseline with current capacity',\n                'week_3_4': 'Increase weight by 5-10% or add 2-3 reps',\n                'week_5_6': 'Progress to more challenging variations',\n                'week_7_8': 'Deload week, then increase volume'\n            },\n            'advanced': {\n                'week_1_2': 'Focus on technique refinement',\n                'week_3_4': 'Periodized loading increases',\n                'week_5_6': 'Advanced movement patterns',\n                'week_7_8': 'Specialization phase'\n            }\n        }\n        \n        return progressions.get(experience_level, progressions['beginner'])\n    \n    def calculate_sets_reps():\n        \"\"\"Calculate appropriate sets and reps based on goals\"\"\"\n        goals_lower = fitness_goals.lower()\n        \n        if 'strength' in goals_lower:\n            return {'sets': '3-5', 'reps': '3-6', 'rest': '2-3 minutes'}\n        elif 'muscle' in goals_lower or 'size' in goals_lower:\n            return {'sets': '3-4', 'reps': '6-12', 'rest': '1-2 minutes'}\n        elif 'endurance' in goals_lower:\n            return {'sets': '2-3', 'reps': '12-20', 'rest': '30-60 seconds'}\n        elif 'weight loss' in goals_lower or 'fat loss' in goals_lower:\n            return {'sets': '3-4', 'reps': '8-15', 'rest': '45-90 seconds'}\n        else:\n            return {'sets': '3', 'reps': '8-12', 'rest': '60-90 seconds'}\n    \n    # Main execution\n    split_type, days_per_week = determine_workout_split()\n    selected_exercises = select_exercises_for_split(split_type, equipment_available)\n    weekly_schedule = create_workout_schedule(split_type, days_per_week)\n    progression_plan = generate_progression_plan()\n    sets_reps_scheme = calculate_sets_reps()\n    \n    # Generate warm-up and cool-down\n    warmup = [\n        '5-10 minutes light cardio (walking, marching)',\n        'Dynamic stretching (arm circles, leg swings)',\n        'Joint mobility (shoulder rolls, hip circles)',\n        'Activation exercises for target muscles'\n    ]\n    \n    cooldown = [\n        '5-10 minutes light cardio or walking',\n        'Static stretching (hold 20-30 seconds)',\n        'Deep breathing and relaxation',\n        'Foam rolling if available'\n    ]\n    \n    # Create output\n    output = {\n        'workout_plan_summary': {\n            'split_type': split_type,\n            'days_per_week': days_per_week,\n            'session_duration': time_per_session,\n            'experience_level': experience_level,\n            'primary_goals': fitness_goals\n        },\n        'weekly_schedule': weekly_schedule,\n        'exercise_selection': selected_exercises,\n        'sets_and_reps': sets_reps_scheme,\n        'warm_up_routine': warmup,\n        'cool_down_routine': cooldown,\n        'progression_plan': progression_plan,\n        'equipment_utilized': equipment_available,\n        'safety_considerations': {\n            'form_first': 'Always prioritize proper form over weight or reps',\n            'listen_to_body': 'Stop if you feel pain (not muscle fatigue)',\n            'gradual_progression': 'Increase intensity gradually each week',\n            'rest_days': 'Include at least 1-2 rest days per week',\n            'hydration': 'Stay hydrated before, during, and after workouts'\n        },\n        'modifications_for_limitations': {\n            'general': 'Consult healthcare provider for specific limitations',\n            'joint_issues': 'Focus on low-impact variations',\n            'back_problems': 'Avoid loaded spinal flexion',\n            'knee_issues': 'Limit deep knee bends, use partial range of motion'\n        },\n        'success_tips': [\n            'Track your workouts to monitor progress',\n            'Focus on consistency over perfection',\n            'Prepare workout clothes the night before',\n            'Find a workout buddy for accountability',\n            'Celebrate small wins and milestones',\n            'Adjust the plan as you progress and learn'\n        ]\n    }\n    \n    return json.dumps(output, indent=2)\n\n# Execute the function\nresult = create_workout_routine()\nprint(result)"
          }
        },
        "formInput": {
          "__version": "1.0",
          "schema": {
            "containers": [],
            "elements": [
              {
                "fieldName": "fitness_goals",
                "id": "fitness_goals_input",
                "label": "Fitness Goals",
                "type": "Text",
                "isRequired": true,
                "props": {
                  "placeholder": "What are your fitness goals? (e.g., weight loss, muscle gain, strength, endurance, general fitness...)"
                }
              },
              {
                "fieldName": "equipment_available",
                "id": "equipment_available_input",
                "label": "Equipment Available",
                "type": "Text",
                "isRequired": true,
                "props": {
                  "placeholder": "What equipment do you have access to? (e.g., dumbbells, resistance bands, gym membership, bodyweight only...)",
                  "minRows": 2
                }
              },
              {
                "fieldName": "schedule_availability",
                "id": "schedule_availability_input",
                "label": "Schedule Availability",
                "type": "Text",
                "isRequired": true,
                "props": {
                  "placeholder": "How many days per week can you work out? What days work best for you?"
                }
              },
              {
                "fieldName": "experience_level",
                "id": "experience_level_input",
                "label": "Experience Level",
                "type": "Selector",
                "isRequired": true,
                "props": {
                  "options": ["beginner", "intermediate", "advanced"],
                  "defaultValue": "beginner"
                }
              },
              {
                "fieldName": "time_per_session",
                "id": "time_per_session_input",
                "label": "Time Per Session",
                "type": "Selector",
                "isRequired": true,
                "props": {
                  "options": ["15-30 minutes", "30-45 minutes", "45-60 minutes", "60+ minutes"],
                  "defaultValue": "30-45 minutes"
                }
              },
              {
                "fieldName": "physical_limitations",
                "id": "physical_limitations_input",
                "label": "Physical Limitations (Optional)",
                "type": "Text",
                "isRequired": false,
                "props": {
                  "placeholder": "Any injuries, physical limitations, or areas to avoid?",
                  "minRows": 2
                }
              },
              {
                "fieldName": "workout_preferences",
                "id": "workout_preferences_input",
                "label": "Workout Preferences (Optional)",
                "type": "Text",
                "isRequired": false,
                "props": {
                  "placeholder": "Any specific preferences? (e.g., prefer cardio, hate burpees, love functional movements...)",
                  "minRows": 2
                }
              }
            ]
          }
        },
        "formOutput": {
          "__version": "1.0",
          "schema": {
            "containers": [],
            "elements": [
              {
                "fieldName": "response",
                "id": "complete_workout_plan_output",
                "label": "Complete Workout Plan",
                "type": "Text"
              },
              {
                "fieldName": "weeklySchedule",
                "id": "weekly_schedule_output",
                "label": "Weekly Workout Schedule",
                "type": "Text"
              },
              {
                "fieldName": "exerciseDetails",
                "id": "exercise_details_output",
                "label": "Exercise Selection & Instructions",
                "type": "Text"
              },
              {
                "fieldName": "progressionPlan",
                "id": "progression_plan_output",
                "label": "Progression Plan",
                "type": "Text"
              }
            ]
          }
        },
        "executionStrategy": "deterministic"
      },
      "translations": [
        {
          "id": "7829564732190847128",
          "language": "en",
          "name": "Workout Routine Builder",
          "description": "Creates personalized workout plans based on fitness goals and equipment. Balances muscle groups, includes rest days, provides progression guidance with safety considerations and modifications for limitations.",
          "instructions": "1. Define your fitness goals\n2. List available equipment\n3. Specify schedule availability\n4. Choose experience level\n5. Set time per session\n6. Note any physical limitations (optional)\n7. Add workout preferences (optional)\n\nThe builder will create:\n- Personalized workout split and schedule\n- Exercise selection based on equipment\n- Sets, reps, and rest recommendations\n- Warm-up and cool-down routines\n- Progressive overload plan\n- Safety considerations and modifications\n- Success tips and tracking guidance\n\nPerfect for fitness beginners, experienced athletes, and anyone looking for structured workout programming."
        }
      ]
    }
  ]
}